marsbots/__init__.py
marsbots/config.py
marsbots/constants.py
marsbots/discord_utils.py
marsbots/exceptions.py
marsbots/language_models.py
marsbots/models.py
marsbots/modifiers.py
marsbots/settings_manager.py
marsbots/text_postprocessors.py
marsbots/util.py
marsbots-0.2.1.dist-info/WHEEL
marsbots-0.2.1.dist-info/METADATA
marsbots-0.2.1.dist-info/RECORD
