Metadata-Version: 2.1
Name: marsbots
Version: 0.2.1
Summary: The core framework for cool Martian bots.
Author-email: Jonathan Miller <jon@jmill.dev>
Requires-Dist: cohere
Requires-Dist: requests
Requires-Dist: openai
Requires-Dist: python-dotenv
Requires-Dist: py-cord==2.0.0
Requires-Dist: black ; extra == "dev"
Requires-Dist: pytest ; extra == "dev"
Requires-Dist: mypy ; extra == "dev"
Requires-Dist: pre-commit ; extra == "dev"
Requires-Dist: flake8 ; extra == "dev"
Provides-Extra: dev
